{
    "commit_hash": "cbf32c5506706bd84a8506d3cf1e3f2fe9089304",
    "env_name": "virtualenv-py3.13",
    "date": 1784563590000,
    "params": {
        "arch": "AMD64",
        "cpu": "Intel(R) Core(TM) Ultra 9 285K (24 physical cores, 24 logical)",
        "gpu": "NVIDIA NVIDIA RTX PRO 6000 Blackwell Workstation Edition",
        "machine": "newton-benchmark-machine-d773f8a4",
        "num_cpu": "24",
        "os": "Windows 11 version 10.0.26200",
        "ram": "64GB",
        "python": "3.13"
    },
    "python": "3.13",
    "requirements": {},
    "env_vars": {},
    "result_columns": [
        "result",
        "params",
        "version",
        "started_at",
        "duration",
        "stats_ci_99_a",
        "stats_ci_99_b",
        "stats_q_25",
        "stats_q_75",
        "stats_number",
        "stats_repeat",
        "samples",
        "profile"
    ],
    "results": {
        "compilation.bench_example_load.SlowExampleBasicUrdf.time_load": [
            [
                13.87591324999994
            ],
            [],
            "c8e96aea345de87f484e4ed6e86421603d52ec779120a3fabd839464dfb51e39",
            1784566544719,
            64.891,
            [
                -17.432
            ],
            [
                49.451
            ],
            [
                4.8511
            ],
            [
                25.035
            ],
            [
                1
            ],
            [
                4
            ]
        ],
        "compilation.bench_example_load.SlowExampleClothFranka.time_load": [
            [
                35.013417499999974
            ],
            [],
            "a6a2562647fb69702746b637db6c23fa382b05b0e97cee7afbb7ba6592a83518",
            1784566572876,
            155.28,
            [
                -43.132
            ],
            [
                120.38
            ],
            [
                11.086
            ],
            [
                62.554
            ],
            [
                1
            ],
            [
                4
            ]
        ],
        "compilation.bench_example_load.SlowExampleClothTwist.time_load": [
            [
                18.64507269999993
            ],
            [],
            "6b93c89629e18ae89ec3308320451db50eb83f24977a80a69f364b73d435435b",
            1784566642980,
            76.483,
            [
                -16.548
            ],
            [
                54.403
            ],
            [
                6.848
            ],
            [
                30.724
            ],
            [
                1
            ],
            [
                4
            ]
        ],
        "compilation.bench_example_load.SlowExampleRobotAnymal.time_load": [
            [
                31.3749712500001
            ],
            [],
            "7f67d241c037d76eccd4b56077ac053d751b82828d090cfbeb9001d0088152bc",
            1784566680469,
            134.12,
            [
                -16.681
            ],
            [
                83.336
            ],
            [
                16.434
            ],
            [
                48.269
            ],
            [
                1
            ],
            [
                4
            ]
        ],
        "compilation.bench_example_load.SlowExampleRobotCartpole.time_load": [
            [
                23.324398499999973
            ],
            [],
            "156564a71da0483e487b79b3529bc50e31f7281c494a48b9ca2d12300094be02",
            1784566743463,
            100.58,
            [
                -11.85
            ],
            [
                61.729
            ],
            [
                12.533
            ],
            [
                35.73
            ],
            [
                1
            ],
            [
                4
            ]
        ],
        "setup.bench_sdf.FastBuildSdf.time_build_sdf": [
            [
                0.25811310000011645,
                0.14407339999996793,
                0.13173359999996137
            ],
            [
                [
                    "32",
                    "64",
                    "128"
                ]
            ],
            "92f72f96438ffd9ad0dee8e00d73a0a6991544fec74f7f5739e05ad473136aa1",
            1784566930508,
            23.666,
            [
                0.2574,
                0.14361,
                0.13047
            ],
            [
                0.26133,
                0.14645,
                0.14421
            ],
            [
                0.25763,
                0.14401,
                0.13114
            ],
            [
                0.25822,
                0.14446,
                0.13199
            ],
            [
                1,
                1,
                1
            ],
            [
                10,
                10,
                10
            ]
        ],
        "simulation.bench_anymal.FastExampleAnymalPretrained.time_simulate": [
            [
                0.0650751499999842
            ],
            [],
            "75c29742e27150b74bf2fb9266a43bc095106bfc7a54ed4028f5275c88311b78",
            1784566941998,
            64.576,
            [
                0.06183
            ],
            [
                0.068689
            ],
            [
                0.063394
            ],
            [
                0.066863
            ],
            [
                1
            ],
            [
                6
            ]
        ],
        "simulation.bench_cable.FastExampleCablePile.time_simulate": [
            [
                0.131437099999971
            ],
            [],
            "38579de24aa1852dd217c842dc29042fe4671b747fb616437af39fb2e8604988",
            1784566968391,
            36.365,
            [
                0.13047
            ],
            [
                0.13253
            ],
            [
                0.13115
            ],
            [
                0.13178
            ],
            [
                1
            ],
            [
                4
            ]
        ],
        "simulation.bench_cloth.FastExampleClothManipulation.time_simulate": [
            [
                0.475219299999992
            ],
            [],
            "1369873c0a88c16d3821097693638b7a5a3586fdfb9a79f8664f39368d529c73",
            1784566985531,
            115.34,
            [
                0.47214
            ],
            [
                0.48421
            ],
            [
                0.47454
            ],
            [
                0.47557
            ],
            [
                1
            ],
            [
                6
            ]
        ],
        "simulation.bench_cloth.FastExampleClothTwist.time_simulate": [
            [
                0.8287901000000488
            ],
            [],
            "4550069ca84ba0bd50f608a46dad4a7d29ab17d08b7bed62ceea9f55e1c73ee0",
            1784567038021,
            27.383,
            [
                0.82518
            ],
            [
                0.82996
            ],
            [
                0.82836
            ],
            [
                0.82934
            ],
            [
                1
            ],
            [
                10
            ]
        ],
        "simulation.bench_contacts.FastExampleContactPyramidDefaults.time_simulate": [
            [
                0.05196764999993775
            ],
            [],
            "5b2a5503945a50c99a14b5e5ff6eeba0b8ec8251d67bf4de83b53e82fd7b5388",
            1784567051241,
            37.319,
            [
                0.050125
            ],
            [
                0.053935
            ],
            [
                0.051413
            ],
            [
                0.052585
            ],
            [
                1
            ],
            [
                4
            ]
        ],
        "simulation.bench_cpu.CpuIKFranka.time_solve": [
            [
                0.2577512000000297
            ],
            [],
            "9fcf20853dc25c179cf22edc84aaecfbc94de82b1f4b033cce852ac472cd553c",
            1784567069424,
            17.732,
            [
                0.25566
            ],
            [
                0.26148
            ],
            [
                0.25738
            ],
            [
                0.26013
            ],
            [
                1
            ],
            [
                6
            ]
        ],
        "simulation.bench_cpu.CpuMuJoCoAnt.time_simulate": [
            [
                1.0596897000000354
            ],
            [],
            "0a22cae57e12fedfe0c13401c99f74103930eddc22cb682f7ea0c645fea34fab",
            1784567078270,
            38.481,
            [
                0.92509
            ],
            [
                1.3682
            ],
            [
                1.0382
            ],
            [
                1.2736
            ],
            [
                1
            ],
            [
                6
            ]
        ],
        "simulation.bench_cpu.CpuXPBDQuadruped.time_simulate": [
            [
                0.02296400000000176
            ],
            [],
            "54b6dd283508ea5212d65e1e09425583d291e6a060bd4cfa3e7626e86079f450",
            1784567097875,
            13.893,
            [
                0.022905
            ],
            [
                0.023015
            ],
            [
                0.022929
            ],
            [
                0.02299
            ],
            [
                1
            ],
            [
                6
            ]
        ],
        "simulation.bench_heightfield.HeightfieldCollision.time_simulate": [
            [
                0.08429795000006379
            ],
            [],
            "6d62f8706ec6d05d0274666772150be21a893c0a6f051f33c06bb1f8b3c817b6",
            1784567104822,
            19.144,
            [
                0.083137
            ],
            [
                0.084748
            ],
            [
                0.083752
            ],
            [
                0.084575
            ],
            [
                1
            ],
            [
                16
            ]
        ],
        "simulation.bench_ik.FastIKSolve.time_solve": [
            [
                0.08072735000001785
            ],
            [
                [
                    "512"
                ]
            ],
            "e00213950917f07ae44e3e993493cfcb1730b7eaba5277047565a289f98c1f73",
            1784567113584,
            36.517,
            [
                0.079808
            ],
            [
                0.080937
            ],
            [
                0.079833
            ],
            [
                0.080918
            ],
            [
                1
            ],
            [
                12
            ]
        ],
        "simulation.bench_inverse_dynamics.FastInverseDynamics.time_eval_inverse_dynamics_force": [
            [
                0.4133997000000136
            ],
            [],
            "9f1873a9ea3ce3d13d0a7cff5fe4c94cdaa60c47690cd182fc63ff4216688119",
            1784567131436,
            24.174,
            [
                0.40925
            ],
            [
                0.41788
            ],
            [
                0.41056
            ],
            [
                0.41559
            ],
            [
                1
            ],
            [
                12
            ]
        ],
        "simulation.bench_inverse_dynamics.FastInverseDynamics.time_eval_inverse_dynamics_passive": [
            [
                0.3988780999999335
            ],
            [],
            "f30af9c4867af17886ff758d055b4a5325385e407a8a2465b1d577e8e0ca47c7",
            1784567143408,
            23.392,
            [
                0.39815
            ],
            [
                0.4001
            ],
            [
                0.39856
            ],
            [
                0.39935
            ],
            [
                1
            ],
            [
                12
            ]
        ],
        "simulation.bench_kamino.FastDRLegs.time_simulate": [
            [
                1.3960731000000237
            ],
            [],
            "5cfc5255e143308d7271e21566a3229823476fd0a40eea57046aeac59d8abf9e",
            1784567154961,
            81.407,
            [
                1.3861
            ],
            [
                1.4049
            ],
            [
                1.3937
            ],
            [
                1.3979
            ],
            [
                1
            ],
            [
                4
            ]
        ],
        "simulation.bench_quadruped_xpbd.FastExampleQuadrupedXPBD.time_simulate": [
            [
                0.7557096000000456
            ],
            [],
            "50d0cd3276e6b4626370aa795870defa62f275117a504676f0ca58280e23d9ac",
            1784567416855,
            24.921,
            [
                0.75431
            ],
            [
                0.75634
            ],
            [
                0.75492
            ],
            [
                0.75593
            ],
            [
                1
            ],
            [
                20
            ]
        ],
        "simulation.bench_selection.FastExampleSelectionCartpoleMuJoCo.time_simulate": [
            [
                0.4004299499999888
            ],
            [],
            "1d5ae94d0fbd9942b54483081a9ad25b2e28122d1c6749b38c297816aa125377",
            1784567429371,
            30.9,
            [
                0.3928
            ],
            [
                0.41526
            ],
            [
                0.39396
            ],
            [
                0.41311
            ],
            [
                1
            ],
            [
                20
            ]
        ],
        "simulation.bench_sensor_tiled_camera.FastSensorTiledCamera.time_render_color_depth": [
            [
                0.45880104999992
            ],
            [
                [
                    "64"
                ],
                [
                    "4096"
                ],
                [
                    "50"
                ]
            ],
            "27cce50353bc75bb6eb44a254ebda442e40274ae605a844122fd136c1ac499a3",
            1784567443919,
            39.855,
            [
                0.45833
            ],
            [
                0.45925
            ],
            [
                0.45856
            ],
            [
                0.45904
            ],
            [
                1
            ],
            [
                6
            ]
        ],
        "simulation.bench_sensor_tiled_camera.FastSensorTiledCamera.time_render_color_only": [
            [
                0.4562603000001104
            ],
            [
                [
                    "64"
                ],
                [
                    "4096"
                ],
                [
                    "50"
                ]
            ],
            "0d85c283f12a948aba5f1d513447e1719bd57b756fda555cf7af49fdec26ff2f",
            1784567463474,
            32.226,
            [
                0.4558
            ],
            [
                0.45662
            ],
            [
                0.45604
            ],
            [
                0.45639
            ],
            [
                1
            ],
            [
                6
            ]
        ],
        "simulation.bench_sensor_tiled_camera.FastSensorTiledCamera.time_render_depth_only": [
            [
                0.19720359999996617
            ],
            [
                [
                    "64"
                ],
                [
                    "4096"
                ],
                [
                    "50"
                ]
            ],
            "484315cde34bdb94c1bbcbac027a7951a644baefe05245ffc4d23c25471d2ff1",
            1784567479518,
            36.584,
            [
                0.19642
            ],
            [
                0.1984
            ],
            [
                0.19691
            ],
            [
                0.19787
            ],
            [
                1
            ],
            [
                8
            ]
        ],
        "simulation.bench_sensor_tiled_camera.FastSensorTiledCameraPixel.time_render_color_depth": [
            [
                0.13579854999994723
            ],
            [
                [
                    "64"
                ],
                [
                    "4096"
                ],
                [
                    "50"
                ]
            ],
            "27cce50353bc75bb6eb44a254ebda442e40274ae605a844122fd136c1ac499a3",
            1784567497583,
            42.472,
            [
                0.13492
            ],
            [
                0.13603
            ],
            [
                0.13536
            ],
            [
                0.13591
            ],
            [
                1
            ],
            [
                8
            ]
        ],
        "simulation.bench_sensor_tiled_camera.FastSensorTiledCameraPixel.time_render_color_only": [
            [
                0.1317375499999116
            ],
            [
                [
                    "64"
                ],
                [
                    "4096"
                ],
                [
                    "50"
                ]
            ],
            "0d85c283f12a948aba5f1d513447e1719bd57b756fda555cf7af49fdec26ff2f",
            1784567518622,
            35.583,
            [
                0.13038
            ],
            [
                0.13264
            ],
            [
                0.13112
            ],
            [
                0.13194
            ],
            [
                1
            ],
            [
                8
            ]
        ],
        "simulation.bench_sensor_tiled_camera.FastSensorTiledCameraPixel.time_render_depth_only": [
            [
                0.07321524999997564
            ],
            [
                [
                    "64"
                ],
                [
                    "4096"
                ],
                [
                    "50"
                ]
            ],
            "484315cde34bdb94c1bbcbac027a7951a644baefe05245ffc4d23c25471d2ff1",
            1784567536500,
            35.398,
            [
                0.07289
            ],
            [
                0.074523
            ],
            [
                0.073073
            ],
            [
                0.07345
            ],
            [
                1
            ],
            [
                8
            ]
        ],
        "simulation.bench_sensor_tiled_camera.TiledCameraQuadruped.time_render_color_depth": [
            [
                0.3316973999999391
            ],
            [
                [
                    "64"
                ],
                [
                    "4096"
                ],
                [
                    "50"
                ]
            ],
            "27cce50353bc75bb6eb44a254ebda442e40274ae605a844122fd136c1ac499a3",
            1784567554236,
            32.492,
            [
                0.33101
            ],
            [
                0.33225
            ],
            [
                0.33149
            ],
            [
                0.33185
            ],
            [
                1
            ],
            [
                10
            ]
        ],
        "simulation.bench_sensor_tiled_camera.TiledCameraQuadruped.time_render_color_only": [
            [
                0.3281789500000514
            ],
            [
                [
                    "64"
                ],
                [
                    "4096"
                ],
                [
                    "50"
                ]
            ],
            "0d85c283f12a948aba5f1d513447e1719bd57b756fda555cf7af49fdec26ff2f",
            1784567570422,
            32.555,
            [
                0.32736
            ],
            [
                0.32956
            ],
            [
                0.32796
            ],
            [
                0.3283
            ],
            [
                1
            ],
            [
                10
            ]
        ],
        "simulation.bench_sensor_tiled_camera.TiledCameraQuadruped.time_render_depth_only": [
            [
                0.13526920000003884
            ],
            [
                [
                    "64"
                ],
                [
                    "4096"
                ],
                [
                    "50"
                ]
            ],
            "484315cde34bdb94c1bbcbac027a7951a644baefe05245ffc4d23c25471d2ff1",
            1784567586720,
            29.841,
            [
                0.13499
            ],
            [
                0.13563
            ],
            [
                0.13516
            ],
            [
                0.13532
            ],
            [
                1
            ],
            [
                10
            ]
        ],
        "simulation.bench_sensor_tiled_camera.TiledCameraShapes256.time_render_color_depth": [
            [
                0.26653505000001587
            ],
            [
                [
                    "64"
                ],
                [
                    "4096"
                ],
                [
                    "50"
                ]
            ],
            "27cce50353bc75bb6eb44a254ebda442e40274ae605a844122fd136c1ac499a3",
            1784567601622,
            64.632,
            [
                0.25212
            ],
            [
                0.28095
            ],
            [
                0.26639
            ],
            [
                0.26668
            ],
            [
                1
            ],
            [
                2
            ]
        ],
        "simulation.bench_sensor_tiled_camera.TiledCameraShapes256.time_render_color_only": [
            [
                0.26467589999992924
            ],
            [
                [
                    "64"
                ],
                [
                    "4096"
                ],
                [
                    "50"
                ]
            ],
            "0d85c283f12a948aba5f1d513447e1719bd57b756fda555cf7af49fdec26ff2f",
            1784567634163,
            63.977,
            [
                0.2497
            ],
            [
                0.27965
            ],
            [
                0.26453
            ],
            [
                0.26483
            ],
            [
                1
            ],
            [
                2
            ]
        ],
        "simulation.bench_sensor_tiled_camera.TiledCameraShapes256.time_render_depth_only": [
            [
                0.08973309999987578
            ],
            [
                [
                    "64"
                ],
                [
                    "4096"
                ],
                [
                    "50"
                ]
            ],
            "484315cde34bdb94c1bbcbac027a7951a644baefe05245ffc4d23c25471d2ff1",
            1784567666236,
            64.293,
            [
                0.062513
            ],
            [
                0.11695
            ],
            [
                0.089461
            ],
            [
                0.090005
            ],
            [
                1
            ],
            [
                2
            ]
        ],
        "simulation.bench_contacts.FastExampleContactHydroWorkingDefaults.time_simulate": [
            [
                0.060178950000135956
            ],
            [],
            "5389daa5fed1f5449fafa713a96cfc36b7e954e6fc823937abc43fcfb2f12c37",
            1784567732041,
            16.575,
            [
                0.059773
            ],
            [
                0.060612
            ],
            [
                0.060064
            ],
            [
                0.060308
            ],
            [
                1
            ],
            [
                4
            ]
        ],
        "simulation.bench_contacts.FastExampleContactSdfDefaults.time_simulate": [
            [
                0.08061930000008033
            ],
            [],
            "75fa33f2d98e88de35f707645ccb9f5c5366ca83ed131b9f85b51bc872a30f16",
            1784567743215,
            11.474,
            [
                0.079461
            ],
            [
                0.081803
            ],
            [
                0.080244
            ],
            [
                0.081007
            ],
            [
                1
            ],
            [
                4
            ]
        ],
        "setup.bench_model.FastInitializeSolver.time_initialize_solver": [
            [
                0.051165399999945294,
                0.1388644999999542,
                0.019502200000033554
            ],
            [
                [
                    "'humanoid'",
                    "'g1'",
                    "'cartpole'"
                ],
                [
                    "256"
                ]
            ],
            "3b89e042bc863172b61d3d39c02f8f67dffe87664041c32c6e277846ed2095dd",
            1784566790428,
            31.161,
            [
                0.04927,
                0.081031,
                0.00099737
            ],
            [
                0.052682,
                0.20737,
                0.042286
            ],
            [
                0.050847,
                0.13617,
                0.018957
            ],
            [
                0.051199,
                0.14956,
                0.023256
            ],
            [
                1,
                1,
                1
            ],
            [
                3,
                3,
                3
            ]
        ],
        "setup.bench_model.FastInitializeViewerGL.time_initialize_renderer": [
            null,
            [
                [
                    "'g1'"
                ],
                [
                    "256"
                ]
            ],
            "6c957e22fbeb7711e6fbdfb6f8053bb4147d24a6d118c46438a961f3a2c8feab",
            1784566821590,
            2.9715
        ],
        "setup.bench_model.KpiInitializeModel.time_initialize_model": [
            [
                2.4358861000000616,
                4.424528099999861,
                0.3740596000000096
            ],
            [
                [
                    "'humanoid'",
                    "'g1'",
                    "'cartpole'"
                ],
                [
                    "8192"
                ]
            ],
            "1eb1943d31536b040079c24c6428a73a866fdab4411562e31dbf0c79bcb18df9",
            1784566824562,
            38.45,
            [
                2.4192,
                4.2416,
                0.33449
            ],
            [
                2.4537,
                4.5747,
                0.42477
            ],
            [
                2.4345,
                4.3948,
                0.37367
            ],
            [
                2.4382,
                4.4297,
                0.3828
            ],
            [
                1,
                1,
                1
            ],
            [
                3,
                3,
                3
            ]
        ],
        "setup.bench_model.KpiInitializeSolver.time_initialize_solver": [
            [
                0.6171377999999095,
                1.10081880000007,
                0.04592170000000806,
                0.237297000000126
            ],
            [
                [
                    "'humanoid'",
                    "'g1'",
                    "'cartpole'",
                    "'ant'"
                ],
                [
                    "8192"
                ]
            ],
            "e358228dda3fc4e02785210c91dce733b1d1aebbce52f3d3ac0dedf2827160a3",
            1784566863013,
            59.383,
            [
                0.40767,
                1.0832,
                0.044168,
                0.22097
            ],
            [
                0.8842,
                1.1151,
                0.048108,
                0.25711
            ],
            [
                0.61452,
                1.0979,
                0.04588,
                0.23671
            ],
            [
                0.66295,
                1.1012,
                0.046287,
                0.2405
            ],
            [
                1,
                1,
                1,
                1
            ],
            [
                3,
                3,
                3,
                3
            ]
        ],
        "setup.bench_model.KpiInitializeViewerGL.time_initialize_renderer": [
            null,
            [
                [
                    "'g1'"
                ],
                [
                    "8192"
                ]
            ],
            "5ba06d80fcf8716093a193bd47034b063820abddda6df221a0f5d2df380f8e01",
            1784566922396,
            8.1106
        ],
        "simulation.bench_kamino.KpiDRLegs.track_simulate": [
            [
                0.026883058300781967
            ],
            [
                [
                    "4096"
                ]
            ],
            "f97a2a73bfc4b72f0cb9112dfee1c26a2aca2d6db02f03df354c5970deabef09",
            1784567193019,
            40.819
        ],
        "simulation.bench_mujoco.FastAllegro.track_simulate": [
            [
                0.0003367684403201565
            ],
            [
                [
                    "8192"
                ]
            ],
            "7deb8426115b4478e0218848034ff1ce843d79f6fa7c3eab3ae47225cea6f22a",
            1784567233837,
            73.383
        ],
        "simulation.bench_mujoco.FastCartpole.track_simulate": [
            [
                2.391323505435139e-05
            ],
            [
                [
                    "8192"
                ]
            ],
            "7deb8426115b4478e0218848034ff1ce843d79f6fa7c3eab3ae47225cea6f22a",
            1784567307220,
            10.1
        ],
        "simulation.bench_mujoco.FastG1.track_simulate": [
            [
                0.00032695767004042864
            ],
            [
                [
                    "8192"
                ]
            ],
            "7deb8426115b4478e0218848034ff1ce843d79f6fa7c3eab3ae47225cea6f22a",
            1784567317320,
            27.636
        ],
        "simulation.bench_mujoco.FastHumanoid.track_simulate": [
            [
                0.00010307219781680033
            ],
            [
                [
                    "8192"
                ]
            ],
            "7deb8426115b4478e0218848034ff1ce843d79f6fa7c3eab3ae47225cea6f22a",
            1784567344957,
            26.326
        ],
        "simulation.bench_mujoco.FastKitchenG1.track_simulate": [
            [
                0.0019718236289918423
            ],
            [
                [
                    "512"
                ]
            ],
            "7deb8426115b4478e0218848034ff1ce843d79f6fa7c3eab3ae47225cea6f22a",
            1784567371283,
            7.658
        ],
        "simulation.bench_mujoco.FastNewtonOverheadG1.track_simulate": [
            [
                11.967335584459088
            ],
            [
                [
                    "8192"
                ]
            ],
            "fe70e157fca3a62483a36774d09261958a0fedbf90954bc3cd3db4f230fa368d",
            1784567378942,
            18.231
        ],
        "simulation.bench_mujoco.FastNewtonOverheadHumanoid.track_simulate": [
            [
                13.443827166989422
            ],
            [
                [
                    "8192"
                ]
            ],
            "fe70e157fca3a62483a36774d09261958a0fedbf90954bc3cd3db4f230fa368d",
            1784567397172,
            19.683
        ],
        "simulation.bench_viewer.FastViewerGL.time_rendering_frame": [
            null,
            [
                [
                    "'g1'"
                ],
                [
                    "256"
                ]
            ],
            "dc458e762bf26467d1e2af3f425b70413cb7675f9a0d646c652bad3d5bf4a670",
            1784567698943,
            2.9403
        ],
        "simulation.bench_viewer.KpiViewerGL.time_rendering_frame": [
            null,
            [
                [
                    "'g1'"
                ],
                [
                    "8192"
                ]
            ],
            "c25efe60406065ad84bde4908e8f914997f231cfbc4213475b4da9d20809bd87",
            1784567701884,
            8.1963
        ],
        "setup.bench_model.FastInitializeModel.peakmem_initialize_model_cpu": [
            [
                637194240,
                1262342144,
                805605376
            ],
            [
                [
                    "'humanoid'",
                    "'g1'",
                    "'cartpole'"
                ],
                [
                    "256"
                ]
            ],
            "889585d54e5e70fe61ed7e1e066b837180ea8bde16da86aa735ad894f10f63f4",
            1784567713744,
            8.6793
        ],
        "setup.bench_model.FastInitializeModel.time_initialize_model": [
            [
                0.08229220000021087,
                0.8066047000002072,
                0.023263999999926455
            ],
            [
                [
                    "'humanoid'",
                    "'g1'",
                    "'cartpole'"
                ],
                [
                    "256"
                ]
            ],
            "2c5b54190ffe915edf4bedba6e1bda0783dd321f2141a56e52ace85061077198",
            1784567722423,
            9.6173,
            [
                0.080887,
                0.49899,
                0.020717
            ],
            [
                0.084048,
                1.0578,
                0.026144
            ],
            [
                0.082261,
                0.75627,
                0.023097
            ],
            [
                0.082587,
                0.81463,
                0.02368
            ],
            [
                1,
                1,
                1
            ],
            [
                3,
                3,
                3
            ]
        ]
    },
    "durations": {
        "<setup_cache simulation.bench_contacts:88>": 17.670984,
        "<setup_cache simulation.bench_contacts:52>": 5.532856,
        "<setup_cache setup.bench_model:118>": 3.662568
    },
    "version": 2
}